Metadata-Version: 1.0
Name: ezmaker
Version: 0.5
Summary: A useful module
Home-page: UNKNOWN
Author: Martin Gonda
Author-email: martingonda15@gmai.com
License: MIT
Platform: UNKNOWN
